PyPixel/Achievements.py
PyPixel/Auction.py
PyPixel/AuctionPage.py
PyPixel/Cache.py
PyPixel/Errors.py
PyPixel/Firework.py
PyPixel/Guild.py
PyPixel/GuildMember.py
PyPixel/GuildRank.py
PyPixel/Hypixel.py
PyPixel/Key.py
PyPixel/Player.py
PyPixel/PlayerStats.py
PyPixel/SkyBlockProfile.py
PyPixel/SkyBlockProfileMember.py
PyPixel/SkyBlockStats.py
PyPixel/SkywarsStats.py
PyPixel/__init__.py
PyPixel/utils/Hypixel.py
PyPixel/utils/SkyBlock.py
PyPixel/utils/__init__.py
PyPixel/utils/games.py
PyPixel/utils/items.py
pypixel_api-0.2.3.dist-info/LICENSE
pypixel_api-0.2.3.dist-info/METADATA
pypixel_api-0.2.3.dist-info/WHEEL
pypixel_api-0.2.3.dist-info/top_level.txt
pypixel_api-0.2.3.dist-info/RECORD
