Metadata-Version: 2.1
Name: pypixel-api
Version: 0.2.3
Summary: An asynchronous wrapper for the Hypixel API.
Home-page: https://github.com/plun1331/PyPixel
Author: plun1331
License: MIT
Project-URL: Documentation, https://pypixel.readthedocs.io/en/latest/
Project-URL: Issue tracker, https://github.com/plun1331/PyPixel/issues
Platform: UNKNOWN
Classifier: License :: OSI Approved :: MIT License
Classifier: Natural Language :: English
Classifier: Operating System :: OS Independent
Classifier: Programming Language :: Python :: 3.8
Classifier: Topic :: Internet
Classifier: Topic :: Software Development :: Libraries
Classifier: Topic :: Software Development :: Libraries :: Python Modules
Classifier: Topic :: Utilities
Requires-Python: >=3.6
Requires-Dist: aiohttp (~=3.7.3)
Requires-Dist: NBT (~=1.5.0)
